portx/__init__.py
portx-0.0.2.dist-info/LICENCE.txt
portx-0.0.2.dist-info/METADATA
portx-0.0.2.dist-info/WHEEL
portx-0.0.2.dist-info/top_level.txt
portx-0.0.2.dist-info/RECORD
