Metadata-Version: 2.1
Name: portx
Version: 0.0.2
Summary: Python library for the RedRobotics PPX Programmable Port eXpander
Home-page: https://github.com/RedRobotics
Author: Neil Lambeth
Author-email: neil@redrobotics.co.uk
License: UNKNOWN
Platform: UNKNOWN
Classifier: Programming Language :: Python :: 3
Classifier: License :: OSI Approved :: MIT License
Requires-Python: >=3.6
